aiuda/__init__.py
aiuda/main.py
aiuda/tools.py
aiuda/core/__init__.py
aiuda/core/agent_tools.py
aiuda/core/agents.py
aiuda/core/globals.py
aiuda/core/parsers.py
aiuda/core/types.py
examples/__init__.py
examples/spaider.py
examples/tree.py
examples/utils.py
aiuda-0.0.2.dist-info/LICENSE
aiuda-0.0.2.dist-info/METADATA
aiuda-0.0.2.dist-info/WHEEL
aiuda-0.0.2.dist-info/top_level.txt
aiuda-0.0.2.dist-info/RECORD
